README.md
setup.cfg
setup.py
heapapi/__init__.py
heapapi.egg-info/PKG-INFO
heapapi.egg-info/SOURCES.txt
heapapi.egg-info/dependency_links.txt
heapapi.egg-info/requires.txt
heapapi.egg-info/top_level.txt
tests/__init__.py
tests/test_init.py