Metadata-Version: 1.1
Name: heapapi
Version: 0.0.2
Summary: Heap Analytics Python SDK (unofficial)
Home-page: https://github.com/m-vdb/heap-analytics-python-client
Author: Maxime Vdb
Author-email: me@maxvdb.com
License: MIT
Download-URL: https://github.com/m-vdb/heap-analytics-python-client/archive/v0.0.2.tar.gz
Project-URL: Source Code, https://github.com/m-vdb/heap-analytics-python-client
Keywords: heap analytics api sdk
Platform: UNKNOWN
